gphotos_deleter/__init__.py
gphotos_deleter/gphotos_deleter.py
photosifter/__init__.py
photosifter/__main__.py
photosifter/display.py
photosifter/downloader.py
photosifter/image.py
photosifter/image_handler.py
photosifter/remote.py
photosifter/resolver.py
photosifter/sifter.py
photosifter/util.py
photosifter/auth/client_secret.json
photosifter-0.1.3.dist-info/LICENSE
photosifter-0.1.3.dist-info/METADATA
photosifter-0.1.3.dist-info/WHEEL
photosifter-0.1.3.dist-info/entry_points.txt
photosifter-0.1.3.dist-info/top_level.txt
photosifter-0.1.3.dist-info/RECORD
