Metadata-Version: 2.1
Name: photosifter
Version: 0.1.3
Summary: Photo sifter is a simple application, written in Python, for smooth photo sifting and comparison.
Home-page: https://github.com/kulikjak/photosifter
Author: Jakub Kulik
Author-email: kulikjak@gmail.com
License: MIT
Platform: UNKNOWN
Classifier: Development Status :: 4 - Beta
Classifier: Intended Audience :: End Users/Desktop
Classifier: License :: OSI Approved :: MIT License
Classifier: Natural Language :: English
Classifier: Operating System :: MacOS
Classifier: Operating System :: Microsoft :: Windows
Classifier: Operating System :: POSIX
Classifier: Operating System :: Unix
Classifier: Programming Language :: Python :: 3
Classifier: Programming Language :: Python :: 3.6
Classifier: Programming Language :: Python :: 3.7
Classifier: Programming Language :: Python :: 3.8
Classifier: Programming Language :: Python :: 3.9
Classifier: Programming Language :: Python :: 3.10
Classifier: Topic :: Artistic Software
Classifier: Topic :: Multimedia :: Graphics
Requires-Python: >=3.6
Requires-Dist: google-api-python-client (>=2.28.0)
Requires-Dist: google-auth-httplib2 (>=0.1.0)
Requires-Dist: google-auth-oauthlib (>=0.4.6)
Requires-Dist: numpy (>=1.21.3)
Requires-Dist: opencv-python (>=4.2.0.32)
Provides-Extra: gphotos_deleter
Requires-Dist: selenium ; extra == 'gphotos_deleter'
